ExampleDatasets/ExampleDatasets.py
ExampleDatasets/__init__.py
ExampleDatasets/resources/dfRdatasets.csv.gz
ExampleDatasets-0.1.1.dist-info/LICENSE
ExampleDatasets-0.1.1.dist-info/METADATA
ExampleDatasets-0.1.1.dist-info/WHEEL
ExampleDatasets-0.1.1.dist-info/top_level.txt
ExampleDatasets-0.1.1.dist-info/RECORD
