Metadata-Version: 2.1
Name: ExampleDatasets
Version: 0.1.1
Summary: Example datasets from statistics packages.
Home-page: https://github.com/antononcube/Python-packages/tree/main/ExampleDatasets
Author: Anton Antonov
Author-email: antononcube@posteo.net
Keywords: data frame,dataset,example,example dataset,Rdatasets
Classifier: Intended Audience :: Science/Research
Classifier: Intended Audience :: Developers
Classifier: Programming Language :: Python :: 3
Classifier: License :: OSI Approved :: BSD License
Classifier: Intended Audience :: Science/Research
Classifier: Intended Audience :: Developers
Classifier: Operating System :: OS Independent
Requires-Python: >=3.7
License-File: LICENSE
Requires-Dist: pandas
Requires-Dist: xdg
